{"tables":[{"name":"Geo_Lady_Evelyn_20251123_th","table":{"constraints":{"constraints":[{"type":1,"order":9007199254740991,"columns":[{"index":1,"name":"zoom_level","dataType":5,"max":null,"notNull":true,"primaryKey":false,"autoincrement":false,"constraints":{"constraints":[{"type":4,"name":null,"order":1,"sql":"NOT NULL"}],"typedConstraints":{"4":[{"type":4,"name":null,"order":1,"sql":"NOT NULL"}]}},"type":"INTEGER"},{"index":2,"name":"tile_column","dataType":5,"max":null,"notNull":true,"primaryKey":false,"autoincrement":false,"constraints":{"constraints":[{"type":4,"name":null,"order":1,"sql":"NOT NULL"}],"typedConstraints":{"4":[{"type":4,"name":null,"order":1,"sql":"NOT NULL"}]}},"type":"INTEGER"},{"index":3,"name":"tile_row","dataType":5,"max":null,"notNull":true,"primaryKey":false,"autoincrement":false,"constraints":{"constraints":[{"type":4,"name":null,"order":1,"sql":"NOT NULL"}],"typedConstraints":{"4":[{"type":4,"name":null,"order":1,"sql":"NOT NULL"}]}},"type":"INTEGER"}]},{"type":1,"name":null,"order":null,"sql":"UNIQUE (zoom_level, tile_column, tile_row)"}],"typedConstraints":{"1":[{"type":1,"order":9007199254740991,"columns":[{"index":1,"name":"zoom_level","dataType":5,"max":null,"notNull":true,"primaryKey":false,"autoincrement":false,"constraints":{"constraints":[{"type":4,"name":null,"order":1,"sql":"NOT NULL"}],"typedConstraints":{"4":[{"type":4,"name":null,"order":1,"sql":"NOT NULL"}]}},"type":"INTEGER"},{"index":2,"name":"tile_column","dataType":5,"max":null,"notNull":true,"primaryKey":false,"autoincrement":false,"constraints":{"constraints":[{"type":4,"name":null,"order":1,"sql":"NOT NULL"}],"typedConstraints":{"4":[{"type":4,"name":null,"order":1,"sql":"NOT NULL"}]}},"type":"INTEGER"},{"index":3,"name":"tile_row","dataType":5,"max":null,"notNull":true,"primaryKey":false,"autoincrement":false,"constraints":{"constraints":[{"type":4,"name":null,"order":1,"sql":"NOT NULL"}],"typedConstraints":{"4":[{"type":4,"name":null,"order":1,"sql":"NOT NULL"}]}},"type":"INTEGER"}]},{"type":1,"name":null,"order":null,"sql":"UNIQUE (zoom_level, tile_column, tile_row)"}]}},"columns":{"_pkIndex":0,"_tableName":"Geo_Lady_Evelyn_20251123_th","_columns":[{"index":0,"name":"id","dataType":5,"max":null,"notNull":false,"primaryKey":true,"autoincrement":true,"constraints":{"constraints":[{"type":0,"name":null,"order":3,"sql":"PRIMARY KEY"},{"type":7,"name":null,"order":4,"sql":"AUTOINCREMENT"}],"typedConstraints":{"0":[{"type":0,"name":null,"order":3,"sql":"PRIMARY KEY"}],"7":[{"type":7,"name":null,"order":4,"sql":"AUTOINCREMENT"}]}},"type":"INTEGER"},{"index":1,"name":"zoom_level","dataType":5,"max":null,"notNull":true,"primaryKey":false,"autoincrement":false,"constraints":{"constraints":[{"type":4,"name":null,"order":1,"sql":"NOT NULL"}],"typedConstraints":{"4":[{"type":4,"name":null,"order":1,"sql":"NOT NULL"}]}},"type":"INTEGER"},{"index":2,"name":"tile_column","dataType":5,"max":null,"notNull":true,"primaryKey":false,"autoincrement":false,"constraints":{"constraints":[{"type":4,"name":null,"order":1,"sql":"NOT NULL"}],"typedConstraints":{"4":[{"type":4,"name":null,"order":1,"sql":"NOT NULL"}]}},"type":"INTEGER"},{"index":3,"name":"tile_row","dataType":5,"max":null,"notNull":true,"primaryKey":false,"autoincrement":false,"constraints":{"constraints":[{"type":4,"name":null,"order":1,"sql":"NOT NULL"}],"typedConstraints":{"4":[{"type":4,"name":null,"order":1,"sql":"NOT NULL"}]}},"type":"INTEGER"},{"index":4,"name":"tile_data","dataType":10,"max":null,"notNull":true,"primaryKey":false,"autoincrement":false,"constraints":{"constraints":[{"type":4,"name":null,"order":1,"sql":"NOT NULL"}],"typedConstraints":{"4":[{"type":4,"name":null,"order":1,"sql":"NOT NULL"}]}},"type":"BLOB"}],"_custom":false,"_nameToIndex":{},"_columnNames":["id","zoom_level","tile_column","tile_row","tile_data"],"zoomLevelIndex":1,"tileColumnIndex":2,"tileRowIndex":3,"tileDataIndex":4}},"info":{"tableName":"Geo_Lady_Evelyn_20251123_th","tableType":"userTable","count":88,"minZoom":4,"maxZoom":4,"minWebMapZoom":14,"maxWebMapZoom":14,"zoomLevels":1,"tileMatrixSet":{"srsId":100000,"minX":-80.30032348632812,"maxX":-79.77386515299477,"minY":46.88484824286566,"maxY":47.41128921508789},"contents":{"tableName":"Geo_Lady_Evelyn_20251123_th","dataType":"tiles","identifier":"Geo_Lady_Evelyn_20251123_th","description":"","lastChange":"2025-11-29T18:41:00.269Z","minX":-80.30032348632812,"maxX":-80.0689697265625,"minY":47.06427001953125,"maxY":47.41128921508789,"srs":{"name":"unknown","id":100000,"organization":"NONE","organization_coordsys_id":100000,"definition":"GEOGCS[\"unknown\",DATUM[\"North_American_Datum_1983\",SPHEROID[\"GRS 1980\",6378137,298.257222101,AUTHORITY[\"EPSG\",\"7019\"]],AUTHORITY[\"EPSG\",\"6269\"]],PRIMEM[\"Greenwich\",0,AUTHORITY[\"EPSG\",\"8901\"]],UNIT[\"degree\",0.0174532925199433,AUTHORITY[\"EPSG\",\"9122\"]],AXIS[\"Longitude\",EAST],AXIS[\"Latitude\",NORTH]]","description":null}},"srs":{"name":"unknown","id":100000,"organization":"NONE","organization_coordsys_id":100000,"definition":"GEOGCS[\"unknown\",DATUM[\"North_American_Datum_1983\",SPHEROID[\"GRS 1980\",6378137,298.257222101,AUTHORITY[\"EPSG\",\"7019\"]],AUTHORITY[\"EPSG\",\"6269\"]],PRIMEM[\"Greenwich\",0,AUTHORITY[\"EPSG\",\"8901\"]],UNIT[\"degree\",0.0174532925199433,AUTHORITY[\"EPSG\",\"9122\"]],AXIS[\"Longitude\",EAST],AXIS[\"Latitude\",NORTH]]","description":null},"columns":[{"index":0,"name":"id","max":null,"notNull":false,"primaryKey":true,"dataType":5,"displayName":"id"},{"index":1,"name":"zoom_level","max":null,"notNull":true,"primaryKey":false,"dataType":5,"displayName":"zoom_level"},{"index":2,"name":"tile_column","max":null,"notNull":true,"primaryKey":false,"dataType":5,"displayName":"tile_column"},{"index":3,"name":"tile_row","max":null,"notNull":true,"primaryKey":false,"dataType":5,"displayName":"tile_row"},{"index":4,"name":"tile_data","max":null,"notNull":true,"primaryKey":false,"dataType":10,"displayName":"tile_data"}],"columnMap":{"id":{"index":0,"name":"id","max":null,"notNull":false,"primaryKey":true,"dataType":5,"displayName":"id"},"zoom_level":{"index":1,"name":"zoom_level","max":null,"notNull":true,"primaryKey":false,"dataType":5,"displayName":"zoom_level"},"tile_column":{"index":2,"name":"tile_column","max":null,"notNull":true,"primaryKey":false,"dataType":5,"displayName":"tile_column"},"tile_row":{"index":3,"name":"tile_row","max":null,"notNull":true,"primaryKey":false,"dataType":5,"displayName":"tile_row"},"tile_data":{"index":4,"name":"tile_data","max":null,"notNull":true,"primaryKey":false,"dataType":10,"displayName":"tile_data"}}}}]}